Metadata-Version: 2.1
Name: spotii-push-notification
Version: 0.1.6
Summary: Spotii Push Notification
Home-page: UNKNOWN
Author-email: hello@nuclearo.com
License: UNKNOWN
Keywords: Spotii,Push Notification
Platform: UNKNOWN
Requires-Dist: aiohttp
Requires-Dist: django
Requires-Dist: djangorestframework
Requires-Dist: asgiref
